deebot_client/__init__.py
deebot_client/api_client.py
deebot_client/authentication.py
deebot_client/capabilities.py
deebot_client/command.py
deebot_client/commands/__init__.py
deebot_client/commands/json/__init__.py
deebot_client/commands/json/advanced_mode.py
deebot_client/commands/json/auto_empty.py
deebot_client/commands/json/battery.py
deebot_client/commands/json/border_spin.py
deebot_client/commands/json/border_switch.py
deebot_client/commands/json/carpet.py
deebot_client/commands/json/charge.py
deebot_client/commands/json/charge_state.py
deebot_client/commands/json/child_lock.py
deebot_client/commands/json/clean.py
deebot_client/commands/json/clean_count.py
deebot_client/commands/json/clean_logs.py
deebot_client/commands/json/clean_preference.py
deebot_client/commands/json/clear_map.py
deebot_client/commands/json/common.py
deebot_client/commands/json/const.py
deebot_client/commands/json/continuous_cleaning.py
deebot_client/commands/json/cross_map_border_warning.py
deebot_client/commands/json/custom.py
deebot_client/commands/json/cut_direction.py
deebot_client/commands/json/efficiency.py
deebot_client/commands/json/error.py
deebot_client/commands/json/fan_speed.py
deebot_client/commands/json/life_span.py
deebot_client/commands/json/map/__init__.py
deebot_client/commands/json/map/cached_map_info.py
deebot_client/commands/json/map/major_map.py
deebot_client/commands/json/mop_auto_wash_frequency.py
deebot_client/commands/json/moveup_warning.py
deebot_client/commands/json/multimap_state.py
deebot_client/commands/json/network.py
deebot_client/commands/json/ota.py
deebot_client/commands/json/play_sound.py
deebot_client/commands/json/pos.py
deebot_client/commands/json/relocation.py
deebot_client/commands/json/safe_protect.py
deebot_client/commands/json/station_action.py
deebot_client/commands/json/station_state.py
deebot_client/commands/json/stats.py
deebot_client/commands/json/sweep_mode.py
deebot_client/commands/json/true_detect.py
deebot_client-17.0.1.dist-info/METADATA
deebot_client-17.0.1.dist-info/WHEEL
deebot_client-17.0.1.dist-info/licenses/LICENSE.txt
deebot_client-17.0.1.dist-info/RECORD
