Metadata-Version: 2.4
Name: deebot-client
Version: 17.0.1
Classifier: Development Status :: 4 - Beta
Classifier: Intended Audience :: Developers
Classifier: Programming Language :: Python :: 3.13
Classifier: Programming Language :: Python :: 3.14
Classifier: Topic :: Home Automation
Classifier: Topic :: Software Development :: Libraries :: Python Modules
Requires-Dist: aiohttp>=3.13.3,<4.0
Requires-Dist: aiomqtt>=2.5.0,<3.0
Requires-Dist: cachetools>=5.0.0,<7.0
Requires-Dist: defusedxml>=0.7.1
Requires-Dist: orjson>=3.11.3
License-File: LICENSE.txt
Summary: Deebot client library in python 3
Keywords: home,automation,homeassistant,vacuum,robot,deebot,ecovacs
Author-email: Robert Resch <robert@resch.dev>
License-Expression: GPL-3.0-or-later
Requires-Python: >=3.13.0
Project-URL: Bug Reports, https://github.com/DeebotUniverse/client.py/issues
Project-URL: Homepage, https://deebot.readthedocs.io/
Project-URL: Source Code, https://github.com/DeebotUniverse/client.py
